MANIFEST.in
README.md
setup.cfg
setup.py
w3bsite/.version
w3bsite/README.md
w3bsite/__init__.py
w3bsite.egg-info/PKG-INFO
w3bsite.egg-info/SOURCES.txt
w3bsite.egg-info/dependency_links.txt
w3bsite.egg-info/not-zip-safe
w3bsite.egg-info/requires.txt
w3bsite.egg-info/top_level.txt
w3bsite/classes/__init__.py
w3bsite/classes/apps/__init__.py
w3bsite/classes/apps/authentication/__init__.py
w3bsite/classes/apps/authentication/requests.py
w3bsite/classes/apps/authentication/views.py
w3bsite/classes/apps/authentication/html/activate.html
w3bsite/classes/apps/authentication/html/reset.html
w3bsite/classes/apps/authentication/html/signin.html
w3bsite/classes/apps/authentication/html/signup.html
w3bsite/classes/apps/authentication/js/requests.html
w3bsite/classes/apps/authentication/mail/activation.html
w3bsite/classes/apps/authentication/mail/authentication.html
w3bsite/classes/apps/authentication/mail/reset_password.html
w3bsite/classes/apps/defaults/css/styles.html
w3bsite/classes/apps/defaults/html/404.html
w3bsite/classes/apps/defaults/html/500.html
w3bsite/classes/apps/defaults/html/base.html
w3bsite/classes/apps/defaults/html/error.html
w3bsite/classes/apps/defaults/html/examples.html
w3bsite/classes/apps/defaults/html/header.html
w3bsite/classes/apps/defaults/html/maintenance.html
w3bsite/classes/apps/defaults/html/permission_denied.html
w3bsite/classes/apps/defaults/html/privacy_policy.html
w3bsite/classes/apps/defaults/html/topbar.html
w3bsite/classes/apps/defaults/js/defaults.html
w3bsite/classes/apps/defaults/js/firebase.html
w3bsite/classes/apps/logging/__init__.py
w3bsite/classes/apps/logging/logging.py
w3bsite/classes/apps/logging/requests.py
w3bsite/classes/apps/metrics/__init__.py
w3bsite/classes/apps/metrics/metrics.py
w3bsite/classes/apps/metrics/requests.py
w3bsite/classes/apps/metrics/js/metrics.html
w3bsite/classes/apps/payments/__init__.py
w3bsite/classes/apps/payments/requests.py
w3bsite/classes/apps/payments/views.py
w3bsite/classes/apps/payments/html/cancel.html
w3bsite/classes/apps/payments/html/purchase.html
w3bsite/classes/cache/__init__.py
w3bsite/classes/config/__init__.py
w3bsite/classes/daemons/__init__.py
