Metadata-Version: 1.0
Name: w3bsite
Version: 4.56.9
Summary: Some description.
Home-page: http://github.com/vandenberghinc/w3bsite
Author: Daan van den Bergh
Author-email: vandenberghinc.contact@gmail.com
License: MIT
Platform: UNKNOWN
